pyadxcli/__init__.py
pyadxcli/client.py
pyadxcli/utils.py
pyadxcli-0.1.dist-info/DESCRIPTION.rst
pyadxcli-0.1.dist-info/METADATA
pyadxcli-0.1.dist-info/RECORD
pyadxcli-0.1.dist-info/WHEEL
pyadxcli-0.1.dist-info/metadata.json
pyadxcli-0.1.dist-info/top_level.txt
